setup.cfg
setup.py
CDNInvalidation/__init__.py
CDNInvalidation.egg-info/PKG-INFO
CDNInvalidation.egg-info/SOURCES.txt
CDNInvalidation.egg-info/dependency_links.txt
CDNInvalidation.egg-info/entry_points.txt
CDNInvalidation.egg-info/requires.txt
CDNInvalidation.egg-info/top_level.txt