Metadata-Version: 1.1
Name: CDNInvalidation
Version: 1.0.0
Summary: 使指定CloudFront对象缓存失效
Home-page: https://newops.cn/15077893526985.html
Author: wanglin
Author-email: wanglin@dbca.cn
License: GPLv2
Platform: UNKNOWN
Classifier: Programming Language :: Python
Classifier: Programming Language :: Python :: 2.7
